addthalesnumbers/__init__.py
addthalesnumbers/addthalesnumbers.py
addthalesnumbers/cli.py
addthalesnumbers-0.1.3.dist-info/AUTHORS.rst
addthalesnumbers-0.1.3.dist-info/LICENSE
addthalesnumbers-0.1.3.dist-info/METADATA
addthalesnumbers-0.1.3.dist-info/WHEEL
addthalesnumbers-0.1.3.dist-info/entry_points.txt
addthalesnumbers-0.1.3.dist-info/top_level.txt
addthalesnumbers-0.1.3.dist-info/RECORD
