Metadata-Version: 2.1
Name: addthalesnumbers
Version: 0.1.3
Summary: add number for thales
Home-page: https://github.com/Archangelix/addthalesnumbers
Author: Iwan Nugraha
Author-email: iwan.nugraha.e@thalesdigital.io
License: MIT license
Keywords: addthalesnumbers
Platform: UNKNOWN
Classifier: Development Status :: 2 - Pre-Alpha
Classifier: Intended Audience :: Developers
Classifier: License :: OSI Approved :: MIT License
Classifier: Natural Language :: English
Classifier: Programming Language :: Python :: 3
Classifier: Programming Language :: Python :: 3.6
Classifier: Programming Language :: Python :: 3.7
Classifier: Programming Language :: Python :: 3.8
Requires-Python: >=3.6
License-File: LICENSE
License-File: AUTHORS.rst
